abstract_clicks/__init__.py
abstract_clicks/list_cycle.py
abstract_clicks/auto_utils/__init__.py
abstract_clicks/auto_utils/auto_utils.py
abstract_clicks/auto_utils/browser_utils.py
abstract_clicks/auto_utils/click_utils.py
abstract_clicks/auto_utils/imports.py
abstract_clicks/auto_utils/tester.py
abstract_clicks/auto_utils/windowMonitor.py
abstract_clicks/flask_app/__init__.py
abstract_clicks/flask_app/wsgi.py
abstract_clicks/flask_app/getRecieve/__init__.py
abstract_clicks/flask_app/getRecieve/imports.py
abstract_clicks/flask_app/getRecieve/routes/__init__.py
abstract_clicks/flask_app/getRecieve/routes/query_route.py
abstract_clicks/flask_app/getRecieve/routes/response_route.py
abstract_clicks/flask_app/getRecieve/routes/watcher_route.py
abstract_clicks/imports/__init__.py
abstract_clicks/imports/imports.py
abstract_clicks/imports/manager_imports.py
abstract_clicks/junk/__init__.py
abstract_clicks/junk/__main__.py
abstract_clicks/junk/events_recorder.py
abstract_clicks/junk/replay.py
abstract_clicks/junk/utils.py
abstract_clicks/managers/__init__.py
abstract_clicks/managers/shadow_functions.py
abstract_clicks/managers/utils.py
abstract_clicks/managers/window_gui.py
abstract_clicks/managers/changeHandler/__init__.py
abstract_clicks/managers/changeHandler/changeHandler.py
abstract_clicks/managers/clipboardManager/__init__.py
abstract_clicks/managers/clipboardManager/clipboardManager.py
abstract_clicks/managers/clipboardManager/utils.py
abstract_clicks/managers/clipboardManager/shadow_functions/__init__.py
abstract_clicks/managers/clipboardManager/shadow_functions/shadow_copy.py
abstract_clicks/managers/clipboardManager/shadow_functions/shadow_custom.py
abstract_clicks/managers/clipboardManager/shadow_functions/shadow_functions.py
abstract_clicks/managers/clipboardManager/shadow_functions/shadow_main.py
abstract_clicks/managers/clipboardManager/shadow_functions/shadow_monitor.py
abstract_clicks/managers/eventsRecorder/__init__.py
abstract_clicks-0.0.0.41.dist-info/METADATA
abstract_clicks-0.0.0.41.dist-info/WHEEL
abstract_clicks-0.0.0.41.dist-info/top_level.txt
abstract_clicks-0.0.0.41.dist-info/RECORD
