Metadata-Version: 2.4
Name: abstract_clicks
Version: 0.0.0.41
Author: putkoff
Author-email: partners@abstractendeavors.com
Classifier: Development Status :: 3 - Alpha
Classifier: Intended Audience :: Developers
Classifier: License :: OSI Approved :: MIT License
Classifier: Programming Language :: Python :: 3
Classifier: Programming Language :: Python :: 3.11
Requires-Python: >=3.6
Requires-Dist: abstract_utilities
Requires-Dist: abstract_gui
Requires-Dist: keyboard
Requires-Dist: pyautogui
Requires-Dist: mouse
Dynamic: author
Dynamic: author-email
Dynamic: classifier
Dynamic: description
Dynamic: description-content-type
Dynamic: requires-dist
Dynamic: requires-python
